pipeline_diacritizer/__init__.py
pipeline_diacritizer/dataset_preprocessing.py
pipeline_diacritizer/diacritization_model.py
pipeline_diacritizer/pipeline_diacritizer.py
pipeline_diacritizer-1.0.2.dist-info/LICENSE.txt
pipeline_diacritizer-1.0.2.dist-info/METADATA
pipeline_diacritizer-1.0.2.dist-info/WHEEL
pipeline_diacritizer-1.0.2.dist-info/entry_points.txt
pipeline_diacritizer-1.0.2.dist-info/top_level.txt
pipeline_diacritizer-1.0.2.dist-info/RECORD
