Metadata-Version: 2.1
Name: pipeline-diacritizer
Version: 1.0.2
Summary: Command-line application to automatically restore the diacritics of an Arabic text.
Home-page: https://github.com/Hamza5/Pipeline-diacritizer
Author: Hamza Abbad
Author-email: hamza.abbad@whut.edu.cn
License: UNKNOWN
Platform: UNKNOWN
Classifier: Development Status :: 4 - Beta
Classifier: Environment :: Console
Classifier: Intended Audience :: Science/Research
Classifier: License :: OSI Approved :: MIT License
Classifier: Operating System :: OS Independent
Classifier: Programming Language :: Python :: 3
Classifier: Topic :: Scientific/Engineering :: Artificial Intelligence
Classifier: Topic :: Text Processing :: Linguistic
Requires-Python: >=3.4,<3.8
Requires-Dist: tensorflow (<=1.14.0,>=1.11.0)
Requires-Dist: numpy (<=1.16.5,>=1.13.0)
